spreadsheet_to_cpplib/__init__.py
spreadsheet_to_cpplib/asciitext.py
spreadsheet_to_cpplib/clitest.py
spreadsheet_to_cpplib/csvToCpp.py
spreadsheet_to_cpplib/fileOperations.py
spreadsheet_to_cpplib/main.py
spreadsheet_to_cpplib/parse.py
spreadsheet_to_cpplib/run.py
spreadsheet_to_cpplib/template_cmake.py
spreadsheet_to_cpplib/template_headeronly.py
spreadsheet_to_cpplib/template_math.py
spreadsheet_to_cpplib/template_source.py
spreadsheet_to_cpplib/lib/exprtk.hpp
spreadSheet_to_cpplib-1.0.0.dist-info/LICENSE
spreadSheet_to_cpplib-1.0.0.dist-info/METADATA
spreadSheet_to_cpplib-1.0.0.dist-info/WHEEL
spreadSheet_to_cpplib-1.0.0.dist-info/entry_points.txt
spreadSheet_to_cpplib-1.0.0.dist-info/top_level.txt
spreadSheet_to_cpplib-1.0.0.dist-info/RECORD
