Metadata-Version: 2.1
Name: spreadSheet-to-cpplib
Version: 1.0.0
Summary: Convert XLSM CSV to Cpp library project
Home-page: https://github.com/shajeen/spreadsheet-to-cpplib
Author: Sheik S Shajeen Ahamed
Author-email: shajeenahmed@gmail.com
License: GPL-3.0
Project-URL: Bug Tracker, https://github.com/shajeen/spreadsheet-to-cpplib/issues
Platform: UNKNOWN
Classifier: Programming Language :: Python :: 3
Classifier: License :: OSI Approved :: MIT License
Classifier: Operating System :: OS Independent
Requires-Dist: openpyxl
Requires-Dist: pandas
Requires-Dist: numpy
Requires-Dist: xlrd
Requires-Dist: pyfiglet
Requires-Dist: click
